MANIFEST.in
README.txt
setup.py
djangospider/__init__.py
djangospider.egg-info/PKG-INFO
djangospider.egg-info/SOURCES.txt
djangospider.egg-info/dependency_links.txt
djangospider.egg-info/entry_points.txt
djangospider.egg-info/requires.txt
djangospider.egg-info/top_level.txt
djangospider/management/__init__.py
djangospider/management/commands/__init__.py
djangospider/management/commands/closemonitor.py
djangospider/management/commands/runmonitor.py
djangospider/monitor/__init__.py
djangospider/monitor/__init__.pyc
djangospider/monitor/cmdline.py
djangospider/monitor/cmdline.pyc
djangospider/monitor/db.sqlite3
djangospider/monitor/manage.py
djangospider/monitor/manage.pyc
djangospider/monitor/monitor/__init__.py
djangospider/monitor/monitor/__init__.pyc
djangospider/monitor/monitor/settings.py
djangospider/monitor/monitor/settings.pyc
djangospider/monitor/monitor/urls.py
djangospider/monitor/monitor/urls.pyc
djangospider/monitor/monitor/wsgi.py
djangospider/monitor/monitor/wsgi.pyc
djangospider/monitor/mysite/__init__.py
djangospider/monitor/mysite/__init__.pyc
djangospider/monitor/mysite/admin.py
djangospider/monitor/mysite/admin.pyc
djangospider/monitor/mysite/apps.py
djangospider/monitor/mysite/apps.pyc
djangospider/monitor/mysite/models.py
djangospider/monitor/mysite/models.pyc
djangospider/monitor/mysite/tests.py
djangospider/monitor/mysite/tests.pyc
djangospider/monitor/mysite/url.py
djangospider/monitor/mysite/url.pyc
djangospider/monitor/mysite/views.py
djangospider/monitor/mysite/views.pyc
djangospider/monitor/mysite/migrations/__init__.py
djangospider/monitor/mysite/migrations/__init__.pyc
djangospider/monitor/mysite/static/js/Chart.min.js
djangospider/monitor/mysite/static/js/jquery.min.js
djangospider/monitor/mysite/templates/sys.html
djangospider/mycrawl/__init__.py
djangospider/mycrawl/run.py
djangospider/mycrawl/crawler/__init__.py
djangospider/mycrawl/crawler/async_tornado.py
djangospider/mycrawl/crawler/async_twisted.py
djangospider/mycrawl/crawler/thread_phantomjs.py
djangospider/mycrawl/crawler/thread_urllib.py
djangospider/mycrawl/log/__init__.py
djangospider/mycrawl/log/log.py
djangospider/mycrawl/parse/__init__.py
djangospider/mycrawl/parse/parse_response.py
