Metadata-Version: 1.1
Name: djangospider
Version: 0.11
Summary: three ways for spider by python
Home-page: UNKNOWN
Author: alex shu
Author-email: daxia4444@qq.com
License: UNKNOWN
Platform: UNKNOWN
Classifier: Development Status :: 4 - Beta
Classifier: Environment :: Web Environment
Classifier: Intended Audience :: Developers
Classifier: License :: OSI Approved :: BSD License
Classifier: Operating System :: OS Independent
Classifier: Programming Language :: Python :: 2.7
